pyeda/__init__.py
pyeda/inter.py
pyeda/util.py
pyeda/boolalg/__init__.py
pyeda/boolalg/bdd.py
pyeda/boolalg/bfarray.py
pyeda/boolalg/boolfunc.py
pyeda/boolalg/expr.py
pyeda/boolalg/minimization.py
pyeda/boolalg/table.py
pyeda/boolalg/test/__init__.py
pyeda/boolalg/test/test_bdd.py
pyeda/boolalg/test/test_bfarray.py
pyeda/boolalg/test/test_boolfunc.py
pyeda/boolalg/test/test_espresso.py
pyeda/boolalg/test/test_expr.py
pyeda/boolalg/test/test_exxpr.py
pyeda/boolalg/test/test_picosat.py
pyeda/boolalg/test/test_table.py
pyeda/logic/__init__.py
pyeda/logic/addition.py
pyeda/logic/aes.py
pyeda/logic/graycode.py
pyeda/logic/sudoku.py
pyeda/logic/test/__init__.py
pyeda/logic/test/test_addition.py
pyeda/logic/test/test_graycode.py
pyeda/logic/test/test_sudoku.py
pyeda/parsing/__init__.py
pyeda/parsing/boolexpr.py
pyeda/parsing/dimacs.py
pyeda/parsing/lex.py
pyeda/parsing/pla.py
pyeda/parsing/token.py
pyeda/parsing/test/__init__.py
pyeda/parsing/test/test_boolexpr.py
pyeda/parsing/test/test_dimacs.py
pyeda/parsing/test/test_pla.py
pyeda/test/__init__.py
pyeda_pranav-0.0.1.dist-info/METADATA
pyeda_pranav-0.0.1.dist-info/WHEEL
pyeda_pranav-0.0.1.dist-info/top_level.txt
pyeda_pranav-0.0.1.dist-info/RECORD
