Metadata-Version: 2.1
Name: pyeda-pranav
Version: 0.0.1
Summary: pyeda for private use
Author: Pranav Sinha
Author-email: <pranavs1997@gmail.com>
Keywords: python
Classifier: Development Status :: 1 - Planning
Classifier: Intended Audience :: Developers
Classifier: Programming Language :: Python :: 3
Classifier: Operating System :: Unix
Classifier: Operating System :: MacOS :: MacOS X
Classifier: Operating System :: Microsoft :: Windows
